releaseme/__init__.py
releaseme/_cli.py
releaseme/git-tag_to_pypi.yml
cli_release_me-1.1.10.dist-info/METADATA
cli_release_me-1.1.10.dist-info/WHEEL
cli_release_me-1.1.10.dist-info/entry_points.txt
cli_release_me-1.1.10.dist-info/RECORD
