Metadata-Version: 2.4
Name: cli_release-me
Version: 1.1.10
Summary: CLI tool for creating git-tagged versions of Python packages where the version has to be specified exactly once.
Author-email: Thomas Bauwens <thomas.bauwens@kuleuven.be>
